openSDUC/__init__.py
openSDUC/openSDUC_main.py
openSDUC/16g/oUC_Data_Demand_16g.csv
openSDUC/16g/oUC_Data_Duration_16g.csv
openSDUC/16g/oUC_Data_EnergyInflows_16g.csv
openSDUC/16g/oUC_Data_Generation_16g.csv
openSDUC/16g/oUC_Data_MaximumGeneration_16g.csv
openSDUC/16g/oUC_Data_MaximumStorage_16g.csv
openSDUC/16g/oUC_Data_MinimumGeneration_16g.csv
openSDUC/16g/oUC_Data_MinimumStorage_16g.csv
openSDUC/16g/oUC_Data_OperatingReserve_16g.csv
openSDUC/16g/oUC_Data_Parameter_16g.csv
openSDUC/16g/oUC_Data_Scenario_16g.csv
openSDUC/16g/oUC_Dict_Company_16g.csv
openSDUC/16g/oUC_Dict_Generation_16g.csv
openSDUC/16g/oUC_Dict_LoadLevel_16g.csv
openSDUC/16g/oUC_Dict_Scenario_16g.csv
openSDUC/16g/oUC_Dict_Storage_16g.csv
openSDUC/16g/oUC_Dict_Technology_16g.csv
opensduc-1.3.34.dist-info/entry_points.txt
opensduc-1.3.34.dist-info/licenses/LICENSE
opensduc-1.3.34.dist-info/WHEEL
opensduc-1.3.34.dist-info/METADATA
opensduc-1.3.34.dist-info/RECORD
