Metadata-Version: 2.4
Name: openSDUC
Version: 1.3.34
Summary: Open Stochastic Daily Unit Commitment of Thermal and ESS Units (openSDUC) - Version 1.3.34 - January 19, 2026
Home-page: https://pascua.iit.comillas.edu/aramos/openSDUC/index.html
Author: IIT-EnergySystemModels
Author-email: andres.ramos@comillas.edu
Requires-Python: >=3.11
Classifier: Development Status :: 5 - Production/Stable
Classifier: Intended Audience :: Science/Research
Classifier: License :: OSI Approved :: GNU General Public License v3 or later (GPLv3+)
Classifier: Operating System :: OS Independent
Classifier: Programming Language :: Python :: 3.13
License-File: LICENSE
Requires-Dist: matplotlib>=3.10.0
Requires-Dist: pandas>=2.2.2
Requires-Dist: psutil>=5.9.5
Requires-Dist: pyomo>=6.9.5
